UberRidePrediction/__init__.py
UberRidePrediction/prediction_pipeline.py
UberRidePrediction/training_pipeline.py
components/__init__.py
components/data_ingestion.py
components/data_transformation.py
components/model_evaluation.py
components/model_trainer.py
pipeline/__init__.py
pipeline/prediction_pipeline.py
pipeline/training_pipeline.py
utils/__init__.py
utils/pipeline.py
utils/utils.py
UberRidePrediction-0.0.1.dist-info/METADATA
UberRidePrediction-0.0.1.dist-info/WHEEL
UberRidePrediction-0.0.1.dist-info/top_level.txt
UberRidePrediction-0.0.1.dist-info/RECORD
