Metadata-Version: 2.1
Name: UberRidePrediction
Version: 0.0.1
Summary: PineconeUtils is a Python module designed to handle and process data for embedding and indexing using Pinecone, Cohere, and OpenAI services. This utility module makes it easy to load, chunk, prepare, and upsert data into a Pinecone index, making it ideal for applications involving text embedding and retrieval augmented systems(RAG)
Home-page: https://github.com/kowshik24/uber-ride-price-prediction
Author: kowshik24
Author-email: kowshikcseruet1998@gmail.com
License: MIT
Project-URL: Bug Tracker, https://github.com/kowshik24/uber-ride-price-prediction/issues
Classifier: Programming Language :: Python :: 3.7
Classifier: Programming Language :: Python :: 3.8
Classifier: Programming Language :: Python :: 3.9
Classifier: Operating System :: OS Independent
Requires-Python: >=3.7
Requires-Dist: pandas
Requires-Dist: numpy
Requires-Dist: ensure
Requires-Dist: pytest
Requires-Dist: scikit-learn
Requires-Dist: FastAPI
Requires-Dist: uvicorn
Requires-Dist: geopy ==2.4.1
Requires-Dist: xgboost ==2.0.3
Requires-Dist: pytest ==7.1.3
Requires-Dist: tox ==4.15.0
Requires-Dist: black ==22.8.0
Requires-Dist: flake8 ==5.0.4
Requires-Dist: mypy ==0.971
Provides-Extra: testing
Requires-Dist: pytest >=7.1.3 ; extra == 'testing'
Requires-Dist: mypy >=0.971 ; extra == 'testing'
Requires-Dist: flake8 >=5.0.4 ; extra == 'testing'
Requires-Dist: tox ==4.15.0 ; extra == 'testing'
Requires-Dist: black >=22.8.0 ; extra == 'testing'
